Django_auths/__init__.py
Django_auths/module_auth.py
Django_auths/slaveni/db.sqlite3
Django_auths/slaveni/manage.py
Django_auths/slaveni/package.json
Django_auths/slaveni/Slaveni/__pycache__/__init__.cpython-312.pyc
Django_auths/slaveni/Slaveni/__pycache__/__init__.cpython-313.pyc
Django_auths/slaveni/Slaveni/__pycache__/settings.cpython-312.pyc
Django_auths/slaveni/Slaveni/__pycache__/settings.cpython-313.pyc
Django_auths/slaveni/Slaveni/__pycache__/urls.cpython-312.pyc
Django_auths/slaveni/Slaveni/__pycache__/urls.cpython-313.pyc
Django_auths/slaveni/Slaveni/__pycache__/wsgi.cpython-312.pyc
Django_auths/slaveni/Slaveni/__pycache__/wsgi.cpython-313.pyc
Django_auths/slaveni/app/__pycache__/__init__.cpython-312.pyc
Django_auths/slaveni/app/__pycache__/__init__.cpython-313.pyc
Django_auths/slaveni/app/__pycache__/admin.cpython-312.pyc
Django_auths/slaveni/app/__pycache__/admin.cpython-313.pyc
Django_auths/slaveni/app/__pycache__/apps.cpython-312.pyc
Django_auths/slaveni/app/__pycache__/apps.cpython-313.pyc
Django_auths/slaveni/app/__pycache__/forms.cpython-312.pyc
Django_auths/slaveni/app/__pycache__/forms.cpython-313.pyc
Django_auths/slaveni/app/__pycache__/models.cpython-312.pyc
Django_auths/slaveni/app/__pycache__/models.cpython-313.pyc
Django_auths/slaveni/app/__pycache__/urls.cpython-312.pyc
Django_auths/slaveni/app/__pycache__/urls.cpython-313.pyc
Django_auths/slaveni/app/__pycache__/views.cpython-312.pyc
Django_auths/slaveni/app/__pycache__/views.cpython-313.pyc
Django_auths/slaveni/app/migrations/0001_initial.py
Django_auths/slaveni/app/migrations/0002_rename_cancellation_reason_request_other_service_description.py
Django_auths/slaveni/app/migrations/0003_request_status_cancel.py
Django_auths/slaveni/app/migrations/__init__.py
Django_auths/slaveni/app/migrations/__pycache__/0001_initial.cpython-312.pyc
Django_auths/slaveni/app/migrations/__pycache__/0001_initial.cpython-313.pyc
django_toolbar_auths-0.1.2.dist-info/METADATA
django_toolbar_auths-0.1.2.dist-info/WHEEL
django_toolbar_auths-0.1.2.dist-info/top_level.txt
django_toolbar_auths-0.1.2.dist-info/RECORD
